LICENSE.md
README.md
nestor/__init__.py
nestor/datasets/__init__.py
nestor/datasets/excavators.py
nestor/datasets/resources/vocab-excavators2018sexton-1g.csv
nestor/datasets/resources/vocab-excavators2018sexton-2g.csv
nestor/datasets/utils.py
nestor/datasets/vocab.py
nestor/keyword.py
nestor/settings.py
nestor/settings.yaml
nestor/tagplots.py
nestor/tagtrees.py
nestor/utils.py
nist_nestor-0.5.0.dist-info/LICENSE.md
nist_nestor-0.5.0.dist-info/METADATA
nist_nestor-0.5.0.dist-info/WHEEL
nist_nestor-0.5.0.dist-info/RECORD
