Metadata-Version: 2.1
Name: nist-nestor
Version: 0.5.0
Summary: Quantifying tacit human knowledge for Smart Manufacturing Maintenance, for maintnenance-based investigatory analysis
Home-page: https://www.nist.gov/services-resources/software/nestor
Keywords: nlp,smart,manufacturing,maintenance,tag
Author: rtbs-dev
Author-email: rtbs@nist.gov
Requires-Python: >=3.8,<3.10
Classifier: Development Status :: 3 - Alpha
Classifier: Intended Audience :: Manufacturing
Classifier: Intended Audience :: Science/Research
Classifier: License :: Public Domain
Classifier: Programming Language :: Python :: 3
Classifier: Programming Language :: Python :: 3.8
Classifier: Programming Language :: Python :: 3.9
Classifier: Topic :: Scientific/Engineering :: Information Analysis
Requires-Dist: fuzzywuzzy (>=0.18.0,<0.19.0)
Requires-Dist: networkx (>=2.4,<3.0)
Requires-Dist: pandas (>=1,<2)
Requires-Dist: pyyaml (>=5.3.1,<6.0.0)
Requires-Dist: scikit-learn (>=0,<1)
Requires-Dist: tqdm (>=4.48.2,<5.0.0)
